Metadata-Version: 2.0
Name: s-sambuca-core
Version: 1.2.4
Summary: SWAMpy edition - Core components for the SAMBUCA model
Home-page: UNKNOWN
Author: UNKNOWN
Author-email: UNKNOWN
License: Unknown
Keywords: Hydrology Modeling Bathymetry
Platform: any
Classifier: Development Status :: 3 - Alpha
Classifier: Intended Audience :: Science/Research
Classifier: Programming Language :: Python :: 2
Classifier: Programming Language :: Python :: 2.7
Classifier: Programming Language :: Python :: 3
Requires-Dist: future
Requires-Dist: numpy
Requires-Dist: pandas
Requires-Dist: scipy
Requires-Dist: spectral
Requires-Dist: xlrd
Provides-Extra: dev
Requires-Dist: bumpversion; extra == 'dev'
Requires-Dist: check-manifest; extra == 'dev'
Requires-Dist: ipython; extra == 'dev'
Requires-Dist: ipdb; extra == 'dev'
Requires-Dist: pylint; extra == 'dev'
Requires-Dist: sphinx; extra == 'dev'
Requires-Dist: sphinx-rtd-theme; extra == 'dev'
Requires-Dist: wheel; extra == 'dev'
Provides-Extra: test
Requires-Dist: pylint; extra == 'test'
Requires-Dist: pytest; extra == 'test'
Requires-Dist: pytest-sugar; extra == 'test'
